{
  "total": 6961,
  "countries": 167,
  "has_image": 5586,
  "by_type": {
    "platforms.json": 6961
  },
  "by_country": {
    "Albania": 2,
    "Algeria": 18,
    "Angola": 11,
    "Argentina": 73,
    "Australia": 170,
    "Austria": 4,
    "Bahrain": 18,
    "Bangladesh": 18,
    "Belgium": 38,
    "Brazil": 70,
    "Cambodia": 2,
    "Canada": 72,
    "Chile": 43,
    "China": 288,
    "Civilian": 28,
    "Colombia": 21,
    "Commercial": 95,
    "Croatia [1992-]": 5,
    "Cuba": 9,
    "Denmark": 66,
    "Ecuador": 14,
    "Egypt": 66,
    "Finland": 42,
    "France": 253,
    "Germany [DDR, -1990]": 22,
    "Germany [FRG/Reunified]": 127,
    "Greece": 132,
    "India": 98,
    "Indonesia": 59,
    "Iran": 103,
    "Iraq": 70,
    "Israel": 118,
    "Italy": 152,
    "Japan": 148,
    "Jordan": 10,
    "Junkyard": 7,
    "Kuwait": 17,
    "Libya": 21,
    "Malaysia": 35,
    "Mexico": 13,
    "Morocco": 24,
    "NATO": 3,
    "Netherlands": 83,
    "New Zealand": 37,
    "North Korea": 34,
    "Norway": 73,
    "Oman": 19,
    "Pakistan": 59,
    "Peru": 27,
    "Philippines": 23,
    "Poland": 43,
    "Portugal": 26,
    "Qatar": 18,
    "Russia [1992-]": 314,
    "Saudi Arabia": 36,
    "Serbia [1992-]": 8,
    "Singapore": 32,
    "South Africa": 26,
    "South Korea": 82,
    "Soviet Union [-1991]": 384,
    "Spain": 106,
    "Sudan": 6,
    "Sweden": 158,
    "Switzerland": 4,
    "Syria": 15,
    "Taiwan": 72,
    "Thailand": 43,
    "Turkey": 122,
    "UAE": 30,
    "Ukraine [1992-]": 51,
    "United Kingdom": 408,
    "United States": 1573,
    "Venezuela": 36,
    "Yemen [1990-]": 17,
    "Yugoslavia [-1992]": 7,
    "Brunei": 3,
    "Bulgaria": 8,
    "Federated States of Micronesia": 1,
    "Hong Kong": 2,
    "Ireland": 7,
    "Myanmar": 8,
    "Nigeria": 16,
    "Papua New Guinea": 3,
    "Paraguay": 2,
    "Pirates": 7,
    "Romania": 11,
    "Solomon Islands": 2,
    "Sri Lanka": 6,
    "Uruguay": 2,
    "Vietnam [1975-]": 17,
    "Montenegro [1992-]": 3,
    "Tonga": 4,
    "Mozambique": 4,
    "Estonia [1992-]": 4,
    "Guatemala": 4,
    "Zambia": 6,
    "Somalia": 4,
    "Benin [1961-]": 3,
    "Latvia [1992-]": 4,
    "Nepal": 1,
    "European Union [1993-]": 4,
    "Slovakia [1993-]": 4,
    "Kazakhstan [1992-]": 5,
    "Senegal": 5,
    "Unknown": 4,
    "Djibouti [1977-]": 4,
    "Hungary": 6,
    "Chad [1960-]": 3,
    "Lebanon": 4,
    "Iceland": 4,
    "Antigua and Barbuda [1981-]": 4,
    "Honduras": 4,
    "Turkmenistan": 4,
    "Lithuania [1992-]": 5,
    "El Salvador": 4,
    "Maldives [1965-]": 1,
    "Niger": 4,
    "Cote D'Ivoire [1960-]": 4,
    "Suriname [1954-]": 2,
    "Botswana": 4,
    "Barbados [1966-]": 1,
    "Cyprus": 4,
    "North Macedonia [1991-]": 2,
    "Gambia [1965-]": 1,
    "Equatorial Guinea": 5,
    "Kenya": 8,
    "Zimbabwe": 4,
    "Rwanda [1962-]": 1,
    "Panama": 2,
    "Guyana [1966-]": 2,
    "Moldova [1992-]": 4,
    "Uzbekistan": 1,
    "Dominican Republic": 4,
    "Azerbaijan": 15,
    "Tanzania": 4,
    "null": 4,
    "Trinidad and Tobago [1962-]": 4,
    "Togo": 4,
    "Generic": 7,
    "Tajikistan": 2,
    "Fiji": 4,
    "Burkina Faso [1960-]": 2,
    "Ghana": 4,
    "Afghanistan": 4,
    "Timor Leste [1975-]": 4,
    "Belarus [1992-]": 8,
    "Laos": 1,
    "Ethiopia": 7,
    "Czech Republic [1993-]": 7,
    "Malta": 3,
    "Cameroon": 5,
    "Nicaragua": 1,
    "Mali [1960-]": 5,
    "Bahamas": 6,
    "Chechnya [1991-2000]": 4,
    "Slovenia": 4,
    "Bolivia": 1,
    "Uganda": 4,
    "Czechoslovakia  [-1992]": 5,
    "Kyrgyzstan": 1,
    "Georgia [1991-]": 9,
    "Jamaica [1962-]": 4,
    "Costa Rica": 1,
    "DRC/Zaire [1960-]": 4,
    "Armenia": 8,
    "Tunisia": 4,
    "Gabon": 4
  }
}